{"status": true, "status_reason": [], "status_code": [], "1": {"id": "1", "ip_from": "90.223.193.2", "rdns": "te-0-9-0-30-3.er12.enslo.isp.sky.com.", "rtt": 0.64, "address": "no address", "asn": 5607, "network": 0, "hop_latitude": 0, "hop_longitude": 0, "use_next_hop_loc": false, "facility": [], "local_subnet_flag": false, "rule_use": [1]}, "2": {"id": "2", "ip_from": "2.120.11.116", "rdns": "", "rtt": 4.181, "address": "no address", "asn": 5607, "network": 0, "hop_latitude": 0, "hop_longitude": 0, "use_next_hop_loc": false, "facility": [], "local_subnet_flag": false, "rule_use": [6]}, "3": {"id": "3", "ip_from": "2.120.11.116", "rdns": "", "rtt": 100, "address": "no address", "asn": 5607, "network": 0, "hop_latitude": 0, "hop_longitude": 0, "use_next_hop_loc": false, "facility": [], "local_subnet_flag": false, "rule_use": [6]}, "4": {"id": "4", "ip_from": "80.82.243.120", "rdns": "", "rtt": 4.144, "address": "no address", "asn": 28792, "network": 0, "hop_latitude": 51.749144, "hop_longitude": -1.268159, "use_next_hop_loc": false, "facility": [["745"]], "local_subnet_flag": false, "rule_use": [6]}, "5": {"id": "5", "ip_from": "80.82.243.127", "rdns": "", "rtt": 4.599, "address": "no address", "asn": 28792, "network": 0, "hop_latitude": 51.749144, "hop_longitude": -1.268159, "use_next_hop_loc": false, "facility": [["745"]], "local_subnet_flag": false, "rule_use": [6]}, "6": {"id": "6", "ip_from": "80.82.241.134", "rdns": "PROBE6512", "rtt": 7.069, "address": "no address", "asn": 28792, "network": 0, "hop_latitude": 51.7785, "hop_longitude": -1.2725, "use_next_hop_loc": false, "facility": [], "local_subnet_flag": false, "rule_use": [4]}}