{"status": true, "status_reason": ["6519 Exit Facility is 601"], "status_code": 0, "1": {"id": "1", "ip_from": "46.227.207.255", "rdns": "anycast.gateway.faelix.net.", "rtt": 0.351, "address": "no address", "asn": 41495, "network": 0, "hop_latitude": 0, "hop_longitude": 0, "use_next_hop_loc": false, "facility": [], "local_subnet_flag": false, "rule_use": ["get_coords faelix", 1]}, "2": {"id": "2", "ip_from": "46.227.207.255", "rdns": "", "rtt": 100, "address": "no address", "asn": 41495, "network": 0, "hop_latitude": 0, "hop_longitude": 0, "use_next_hop_loc": false, "facility": [], "local_subnet_flag": false, "rule_use": ["get_coords faelix", 6]}, "3": {"id": "3", "ip_from": "46.227.200.244", "rdns": "", "rtt": 0.541, "address": "no address", "asn": 41495, "network": 0, "hop_latitude": 0, "hop_longitude": 0, "use_next_hop_loc": false, "facility": [], "local_subnet_flag": false, "rule_use": ["get_coords faelix", 6]}, "4": {"id": "4", "ip_from": "195.66.244.245", "rdns": "", "rtt": 0.968, "address": "no address", "asn": 28792, "network": 710, "hop_latitude": 53.37912, "hop_longitude": -2.258538, "use_next_hop_loc": false, "facility": [["601"]], "local_subnet_flag": false, "port": "edge3-tdd-man1 xe27", "speed": "1G", "rule_use": [5]}, "5": {"id": "5", "ip_from": "80.82.243.244", "rdns": "", "rtt": 1.111, "address": "no address", "asn": 28792, "network": 0, "hop_latitude": 0, "hop_longitude": 0, "use_next_hop_loc": false, "facility": [], "local_subnet_flag": false, "rule_use": [6]}, "6": {"id": "6", "ip_from": "80.82.242.39", "rdns": "PROBE7094", "rtt": 0.967, "address": "no address", "asn": 28792, "network": 0, "hop_latitude": 53.3795, "hop_longitude": -2.2585, "use_next_hop_loc": false, "facility": [], "local_subnet_flag": false, "rule_use": [4]}}